TuringDSCalculator/__init__.py
turingdscalculator-0.0.3.dist-info/LICENSE
turingdscalculator-0.0.3.dist-info/WHEEL
turingdscalculator-0.0.3.dist-info/METADATA
turingdscalculator-0.0.3.dist-info/RECORD
