Metadata-Version: 2.1
Name: TuringDSCalculator
Version: 0.0.3
Summary: A simple calculator that can perform the following operations:
Author-email: Anton Pham <khoapham2905@gmail.com>
Classifier: License :: OSI Approved :: MIT License
Project-URL: Home, https://github.com/2HO4/Turing-Calculator
